tw_serverinfo/__init__.py
tw_serverinfo/__version__.py
tw_serverinfo/game_servers.py
tw_serverinfo/master_servers.py
tw_serverinfo/network.py
tw_serverinfo/models/__init__.py
tw_serverinfo/models/game_server.py
tw_serverinfo/models/master_server.py
tw_serverinfo/models/player.py
tw_serverinfo/utility/__init__.py
tw_serverinfo/utility/countries.py
Teeworlds_Server_Info-1.0.3.dist-info/LICENSE.md
Teeworlds_Server_Info-1.0.3.dist-info/METADATA
Teeworlds_Server_Info-1.0.3.dist-info/WHEEL
Teeworlds_Server_Info-1.0.3.dist-info/top_level.txt
Teeworlds_Server_Info-1.0.3.dist-info/zip-safe
Teeworlds_Server_Info-1.0.3.dist-info/RECORD
