Metadata-Version: 2.1
Name: Teeworlds-Server-Info
Version: 1.0.3
Summary: Small module to retrieve game servers and player information for the game Teeworlds
Home-page: https://github.com/DaRealFreak/Teeworlds-ServerInfo
Author: DaRealFreak
Author-email: steffen.keuper@web.de
License: MIT
Platform: UNKNOWN
Classifier: Programming Language :: Python :: 3
Classifier: License :: OSI Approved :: MIT License
Classifier: Operating System :: OS Independent
Requires-Dist: pycountry (>=18.5.26)
